pipeless_ai_tf_models/multi_pose_estimation/MultiPoseEstimationLightning.tflite
pipeless_ai_tf_models/multi_pose_estimation/README.md
pipeless_ai_tf_models/multi_pose_estimation/__init__.py
pipeless_ai_tf_models/multi_pose_estimation/lightning.py
pipeless_ai_tf_models/multi_pose_estimation/test.jpeg
pipeless_ai_tf_models/multi_pose_estimation/test.py
pipeless_ai_tf_models/tflite.py
pipeless_ai_tf_models-0.1.0.dist-info/LICENSE
pipeless_ai_tf_models-0.1.0.dist-info/METADATA
pipeless_ai_tf_models-0.1.0.dist-info/WHEEL
pipeless_ai_tf_models-0.1.0.dist-info/RECORD
