Metadata-Version: 2.1
Name: pipeless-ai-tf-models
Version: 0.1.0
Summary: A collection of TensorFlow based models for the Pipeless framework
Home-page: https://pipeless.ai
License: Apache-2.0
Keywords: multimedia,framework,artificial-intelligence,pipeline,developer-tools
Author: Miguel A. Cabrera Minagorri
Author-email: devgorri@gmail.com
Requires-Python: >=3.10,<3.11
Classifier: License :: OSI Approved :: Apache Software License
Classifier: Programming Language :: Python :: 3
Classifier: Programming Language :: Python :: 3.10
Requires-Dist: numpy (>=1.24.0,<1.25.0)
Requires-Dist: pipeless-ai (>=0.1.0,<0.2.0)
Requires-Dist: tensorflow (>=2.12.0,<3.0.0)
Project-URL: Documentation, https://github.com/miguelaeh/pipeless
Project-URL: Repository, https://github.com/miguelaeh/pipeless
